nber_cli/__init__.py
nber_cli/__main__.py
nber_cli/core/__init__.py
nber_cli/core/download/__init__.py
nber_cli/core/download/downloader.py
nber_cli/webui/__init__.py
nber_cli-0.1.4.dist-info/METADATA
nber_cli-0.1.4.dist-info/WHEEL
nber_cli-0.1.4.dist-info/entry_points.txt
nber_cli-0.1.4.dist-info/licenses/LICENSE
nber_cli-0.1.4.dist-info/RECORD
