Metadata-Version: 2.4
Name: nber-cli
Version: 0.1.4
Summary: A command-line tool to download NBER papers.
License-File: LICENSE
Requires-Python: >=3.11
Requires-Dist: aiohttp
Requires-Dist: aiohttp-retry
Requires-Dist: aiosqlite
Requires-Dist: certifi
Requires-Dist: fake-useragent
Requires-Dist: flask
Requires-Dist: orjson
